tfmv/__init__.py
tfmv/client.py
tfmv/error.py
tfmv/main.py
tfmv/state.py
tfmv-1.2.dist-info/LICENCE
tfmv-1.2.dist-info/METADATA
tfmv-1.2.dist-info/WHEEL
tfmv-1.2.dist-info/entry_points.txt
tfmv-1.2.dist-info/top_level.txt
tfmv-1.2.dist-info/RECORD
