Metadata-Version: 2.1
Name: tfmv
Version: 1.2
Summary: Simple tool for moving / renaming resources in one or several terraform configurations.
Home-page: https://gitlab.raisepartner.com/it_group/infra/terraform/tfmv
Author: Vincent Pfister
Author-email: vincent.pfister@raisepartner.com
License: UNKNOWN
Platform: UNKNOWN
Requires-Dist: click
